snowcross/__init__.py
snowcross/aws.py
snowcross/cloud.py
snowcross/errors.py
snowcross/locator.py
snowcross/snowflake.py
tests/fixtures/__init__.py
tests/fixtures/aws.py
tests/fixtures/snowflake.py
tests/helpers/__init__.py
tests/helpers/docker.py
snowcross-0.9.2.dist-info/LICENSE
snowcross-0.9.2.dist-info/METADATA
snowcross-0.9.2.dist-info/WHEEL
snowcross-0.9.2.dist-info/top_level.txt
snowcross-0.9.2.dist-info/RECORD
